{
  "navItems": [
    {
      "name": "Docs",
      "root": "/docs",
      "defaultPath": "/docs/getting-started/introduction",
      "sections": [
        {
          "name": "Getting started",
          "root": "/getting-started",
          "items": [
            {
              "name": "Introduction to Koji",
              "slug": "introduction"
            },
            {
              "name": "Building your first Koji app",
              "slug": "start-tutorial",
              "subItems": [
                {
                  "name": "1. Your first project",
                  "slug": "your-first-project"
                },
                {
                  "name": "2. Using the code editor",
                  "slug": "code-editor"
                },
                {
                  "name": "3. The @withkoji/core package",
                  "slug": "core-package"
                },
                {
                  "name": "4. Your first remix",
                  "slug": "your-first-remix"
                },
                {
                  "name": "5. Introduction to contexts",
                  "slug": "intro-to-contexts"
                },
                {
                  "name": "6. Creating a remixable project",
                  "slug": "remixable-project"
                },
                {
                  "name": "7. Your first app",
                  "slug": "your-first-template"
                }
              ]
            },
            {
              "name": "News for Koji developers",
              "slug": "developer-updates",
              "subItems": [
                {
                  "name": "Recent updates",
                  "slug": "recent-updates"
                },
                {
                  "name": "Earlier in 2021",
                  "slug": "2021-updates"
                },
                {
                  "name": "2020",
                  "slug": "2020-updates"
                }
              ]
            }
          ]
        },
        {
          "name": "Developing apps on Koji",
          "root": "/develop",
          "items": [
            {
              "name": "App development process",
              "slug": "app-dev-process"
            },
            {
              "name": "Project structure and configuration",
              "slug": "projects"
            },
            {
              "name": "Working in the Koji code editor",
              "slug": "editor"
            },
            {
              "name": "Working from your development machine",
              "slug": "local-development",
              "subItems": [
                {
                  "name": "1. Using Git to manage projects",
                  "slug": "use-git"
                },
                {
                  "name": "2. Working locally",
                  "slug": "work-locally"
                },
                {
                  "name": "3. Publishing local projects",
                  "slug": "publish-locally-developed"
                }
              ]
            },
            {
              "name": "Porting existing code to Koji",
              "slug": "port-existing-code"
            },
            {
              "name": "Adding a service",
              "slug": "add-service"
            },
            {
              "name": "Testing and debugging apps",
              "slug": "testing-apps"
            },
            {
              "name": "Managing app versions",
              "slug": "app-versions"
            }
          ]
        },
        {
          "name": "Implementing platform features",
          "root": "/platform",
          "items": [
            {
              "name": "Capturing user input",
              "slug": "capture-user-input"
            },
            {
              "name": "Entitlements",
              "slug": "entitlements"
            },
            {
              "name": "Customizing the thumbnail image",
              "slug": "thumbnail-image"
            },
            {
              "name": "Koji databases",
              "slug": "koji-database"
            }
          ]
        },
        {
          "name": "More guides",
          "root": "/dev-guides",
          "items": [
            {
              "name": "Migrating to the Koji core package",
              "slug": "migrate-koji-core"
            },
            {
              "name": "Example: Creating a game",
              "slug": "game-intro",
              "subItems": [
                {
                  "name": "1. Defining assets",
                  "slug": "game-assets"
                },
                {
                  "name": "2. Creating game objects",
                  "slug": "game-creating-game-objects"
                },
                {
                  "name": "3. Scoring and losing",
                  "slug": "game-scoring-and-losing"
                },
                {
                  "name": "4. Managing difficulty",
                  "slug": "game-managing-difficulty"
                },
                {
                  "name": "5. Adding customization options",
                  "slug": "game-customization"
                },
                {
                  "name": "6. Customizing the preview",
                  "slug": "game-thumbnail-preview"
                },
                {
                  "name": "7. Finishing up",
                  "slug": "game-finishing-up"
                }
              ]
            },
            {
              "name": "Example: Adding in-app purchases to a game",
              "slug": "game-iap-intro",
              "subItems": [
                {
                  "name": "1. Setting up koji.json",
                  "slug": "game-iap-setting-up-koji-json"
                },
                {
                  "name": "2. Creating a payment menu",
                  "slug": "game-iap-payment-menu"
                },
                {
                  "name": "3. Adding the payment logic",
                  "slug": "game-iap-start-purchase"
                },
                {
                  "name": "4. Updating game behavior",
                  "slug": "game-iap-updating-game"
                },
                {
                  "name": "5. Adding customization options",
                  "slug": "game-iap-customization"
                }
              ]
            },
            {
              "name": "Using Koji plugins",
              "slug": "plugins"
            },
            {
              "name": "Using custom domains",
              "slug": "custom-domains"
            },
            {
              "name": "Building custom controls",
              "slug": "build-custom-controls"
            }
          ]
        },
        {
          "name": "Distributing apps",
          "root": "/distribute",
          "items": [
            {
              "name": "Listing in the App Store",
              "slug": "app-store"
            }
          ]
        },
        {
          "name": "About Koji for developers",
          "root": "/about",
          "items": [
            {
              "name": "Glossary",
              "slug": "glossary"
            },
            {
              "name": "Contributing to the developer site",
              "slug": "contribute-koji-developers"
            }
          ]
        }
      ]
    },
    {
      "name": "Reference",
      "root": "/reference",
      "defaultPath": "/reference/core/withkoji-koji-core",
      "sections": [
        {
          "name": "@withkoji/core",
          "root": "/core",
          "items": [
            {
              "name": "Overview",
              "slug": "withkoji-koji-core"
            },
            {
              "name": "Backend",
              "slug": "core-backend-overview",
              "subItems": [
                {
                  "name": "Database",
                  "slug": "core-backend-database"
                },
                {
                  "name": "Dispatch",
                  "slug": "core-backend-dispatch"
                },
                {
                  "name": "IAP",
                  "slug": "core-backend-iap"
                },
                {
                  "name": "Identity",
                  "slug": "core-backend-identity"
                },
                {
                  "name": "Secret",
                  "slug": "core-backend-secret"
                },
                {
                  "name": "Utilities",
                  "slug": "core-backend-utilities"
                }
              ]
            },
            {
              "name": "Frontend",
              "slug": "core-frontend-overview",
              "subItems": [
                {
                  "name": "Analytics",
                  "slug": "core-frontend-analytics"
                },
                {
                  "name": "Dispatch",
                  "slug": "core-frontend-dispatch"
                },
                {
                  "name": "IAP",
                  "slug": "core-frontend-iap"
                },
                {
                  "name": "Identity",
                  "slug": "core-frontend-identity"
                },
                {
                  "name": "PlayerState",
                  "slug": "core-frontend-playerstate"
                },
                {
                  "name": "Remix",
                  "slug": "core-frontend-remix"
                },
                {
                  "name": "UI / Capture",
                  "slug": "core-frontend-ui-capture"
                },
                {
                  "name": "UI / Navigate",
                  "slug": "core-frontend-ui-navigate"
                },
                {
                  "name": "UI / Present",
                  "slug": "core-frontend-ui-present"
                },
                {
                  "name": "UI / Upload",
                  "slug": "core-frontend-ui-upload"
                }
              ]
            }
          ]
        },
        {
          "name": "@withkoji/custom-vcc-sdk",
          "root": "/customvcc",
          "items": [
            {
              "name": "Overview",
              "slug": "withkoji-custom-vcc-sdk"
            },
            {
              "name": "CustomVcc",
              "slug": "customvcc-reference"
            }
          ]
        },
        {
          "name": "Deprecated",
          "root": "/deprecated-packages",
          "items": [
            {
              "name": "Deprecated packages",
              "slug": "deprecated-packages-overview",
              "subItems": [
                {
                  "name": "@withkoji/analytics",
                  "slug": "withkoji-koji-analytics-sdk"
                },
                {
                  "name": "@withkoji/auth",
                  "slug": "withkoji-koji-auth-sdk"
                },
                {
                  "name": "@withkoji/database",
                  "slug": "withkoji-database-package"
                },
                {
                  "name": "@withkoji/dispatch",
                  "slug": "withkoji-dispatch-package"
                },
                {
                  "name": "@withkoji/iap",
                  "slug": "withkoji-koji-iap-package"
                },
                {
                  "name": "@withkoji/user-defaults",
                  "slug": "withkoji-user-defaults-package"
                },
                {
                  "name": "@withkoji/vcc",
                  "slug": "withkoji-vcc-package"
                }
              ]
            }
          ]
        }
      ]
    }
  ]
}
